evtdrivn/__init__.py
evtdrivn/controller.py
evtdrivn/listener.py
evtdrivn/mapping.py
evtdrivn/pool.py
evtdrivn/session.py
evtdrivn/signal.py
evtdrivn/plugins/__init__.py
evtdrivn/plugins/base.py
evtdrivn/plugins/subprocess.py
evtdrivn/plugins/timer.py
EventDriven-0.0.0.dist-info/LICENSE
EventDriven-0.0.0.dist-info/METADATA
EventDriven-0.0.0.dist-info/WHEEL
EventDriven-0.0.0.dist-info/top_level.txt
EventDriven-0.0.0.dist-info/RECORD
