Metadata-Version: 2.1
Name: EventDriven
Version: 0.0.0
Summary: Event Driven Controller.
Home-page: https://github.com/ZSAIm/EventDriven
Author: ZSAIm
Author-email: zzsaim@163.com
License: MIT License
Platform: UNKNOWN
Classifier: Development Status :: 4 - Beta
Classifier: Intended Audience :: Developers
Classifier: License :: OSI Approved :: Apache Software License
Classifier: Programming Language :: Python
Classifier: Programming Language :: Python :: 2.7
Classifier: Programming Language :: Python :: 3
Classifier: Programming Language :: Python :: 3.7
